MANIFEST.in
README.md
setup.py
bossformation/__init__.py
bossformation/cli.py
bossformation/core.py
bossformation.egg-info/PKG-INFO
bossformation.egg-info/SOURCES.txt
bossformation.egg-info/dependency_links.txt
bossformation.egg-info/entry_points.txt
bossformation.egg-info/requires.txt
bossformation.egg-info/top_level.txt