Metadata-Version: 1.1
Name: bossformation
Version: 0.1.0
Summary: Tool to enhance AWS CloudFormation
Home-page: https://github.com/cloudboss/bossformation
Author: Joseph Wright
Author-email: rjosephwright@gmail.com
License: UNKNOWN
Download-URL: https://github.com/cloudboss/bossformation/releases/0.1.0
Platform: UNKNOWN
